plankapy/__init__.py
plankapy/constants.py
plankapy/handlers.py
plankapy/helpers.py
plankapy/interfaces.py
plankapy/models.py
plankapy/routes.py
plankapy-2.2.2.dist-info/licenses/LICENSE
plankapy-2.2.2.dist-info/METADATA
plankapy-2.2.2.dist-info/WHEEL
plankapy-2.2.2.dist-info/top_level.txt
plankapy-2.2.2.dist-info/RECORD
