Metadata-Version: 2.4
Name: plankapy
Version: 2.2.2
Summary: A Python interface for Plankanban
Author-email: Hayden Welch <hwelch@finelines-engineering.com>
Project-URL: Homepage, https://github.com/hwelch-fle/plankapy
Project-URL: Documentation, https://hwelch-fle.github.io/plankapy/plankapy.html
Project-URL: Issues, https://github.com/hwelch-fle/plankapy/issues
Project-URL: Discussions, https://github.com/hwelch-fle/plankapy/discussions
Classifier: Programming Language :: Python :: 3
Classifier: License :: OSI Approved :: GNU Affero General Public License v3 or later (AGPLv3+)
Classifier: Operating System :: OS Independent
Requires-Python: >=3.11
License-File: LICENSE
Dynamic: license-file
